Metadata-Version: 2.1
Name: ridoculous
Version: 0.0.4
Summary: Easily document any object to a markdown file
Home-page: https://www.github.com/tannerburns/ridoculous
Author: Tanner Burns
Author-email: tjburns102@gmail.com
License: UNKNOWN
Platform: UNKNOWN
Classifier: Operating System :: OS Independent
Classifier: Programming Language :: Python :: 3.7
